{
    "key": "group_63ca82d5d289c",
    "title": "Block: Blog Listing 2",
    "fields": [
        {
            "key": "field_63ca82d5d7ded",
            "label": "Block: Blog Listing 2",
            "name": "",
            "aria-label": "",
            "type": "accordion",
            "instructions": "",
            "required": 0,
            "conditional_logic": 0,
            "wrapper": {
                "width": "",
                "class": "",
                "id": ""
            },
            "open": 0,
            "multi_expand": 0,
            "endpoint": 0
        },
        {
            "key": "field_63ca82d5d7dfe",
            "label": "Enable Section",
            "name": "starterkit_enable_section",
            "aria-label": "",
            "type": "true_false",
            "instructions": "",
            "required": 0,
            "conditional_logic": 0,
            "wrapper": {
                "width": "",
                "class": "",
                "id": ""
            },
            "message": "",
            "default_value": 0,
            "ui_on_text": "Enable",
            "ui_off_text": "Disable",
            "ui": 1
        },
        {
            "key": "field_63ca82d5d7e07",
            "label": "Info",
            "name": "",
            "aria-label": "",
            "type": "message",
            "instructions": "",
            "required": 0,
            "conditional_logic": 0,
            "wrapper": {
                "width": "",
                "class": "",
                "id": ""
            },
            "message": "All the post from the posts content type will be display here.",
            "new_lines": "wpautop",
            "esc_html": 0
        }
    ],
    "location": [
        [
            {
                "param": "block",
                "operator": "==",
                "value": "acf\/starter-kit-blog-listing-two"
            }
        ]
    ],
    "menu_order": 0,
    "position": "normal",
    "style": "default",
    "label_placement": "top",
    "instruction_placement": "label",
    "hide_on_screen": "",
    "active": true,
    "description": "",
    "show_in_rest": 0,
    "modified": 1680065200
}